hsmfile/hsmfile.py
hsmfile-0.1.dist-info/LICENSE
hsmfile-0.1.dist-info/METADATA
hsmfile-0.1.dist-info/WHEEL
hsmfile-0.1.dist-info/top_level.txt
hsmfile-0.1.dist-info/RECORD
