Metadata-Version: 2.1
Name: hsmfile
Version: 0.1
Summary: Expedite access to files on a slow network volume
Home-page: https://github.com/hadfieldnz/hsmfile
Author: Mark Hadfield
Author-email: mark.hadfield@niwa.co.nz
License: MIT
Platform: UNKNOWN
Classifier: Programming Language :: Python :: 3
Classifier: License :: OSI Approved :: MIT License
Classifier: Operating System :: OS Independent
Requires-Python: >=3.6
